tkxui/JSONLoader.py
tkxui/Tk.py
tkxui/__init__.py
tkxui/behaviors.py
tkxui/constants.py
tkxui-1.1.5.dist-info/LICENSE
tkxui-1.1.5.dist-info/METADATA
tkxui-1.1.5.dist-info/WHEEL
tkxui-1.1.5.dist-info/top_level.txt
tkxui-1.1.5.dist-info/RECORD
