Metadata-Version: 2.1
Name: tkxui
Version: 1.1.5
Summary: Create modern frameless GUIs with Python, Tkinter and JSON
Home-page: https://github.com/GateMartin/TkXUI
Author: Martin Gate
Author-email: martingate98000@gmail.com
License: UNKNOWN
Project-URL: Bug Tracker, https://github.com/GateMartin/TkXUI/issues
Platform: UNKNOWN
Classifier: Programming Language :: Python :: 3
Classifier: License :: OSI Approved :: MIT License
Classifier: Operating System :: OS Independent
Requires-Python: >=3.2
License-File: LICENSE
